pyVelov/__init__.py
pyVelov/test.py
pyVelov/velov.py
pyVelov/velov_api.py
pyVelov/bikes/__init__.py
pyVelov/bikes/bike.py
pyVelov/bikes/bikes.py
pyVelov/stations/__init__.py
pyVelov/stations/station.py
pyVelov/stations/stations.py
pyVelov-0.0.2.dist-info/METADATA
pyVelov-0.0.2.dist-info/WHEEL
pyVelov-0.0.2.dist-info/top_level.txt
pyVelov-0.0.2.dist-info/RECORD
